epnlink/__init__.py
epnlink/results.py
epnlink/utilities.py
epnlink/templates/16.2/EP_MAPPED.csv
epnlink/templates/16.2/EP_default_zeroed.txt
epnlink-0.0.7.dist-info/LICENSE
epnlink-0.0.7.dist-info/METADATA
epnlink-0.0.7.dist-info/WHEEL
epnlink-0.0.7.dist-info/top_level.txt
epnlink-0.0.7.dist-info/RECORD
