Metadata-Version: 2.1
Name: epnlink
Version: 0.0.7
Summary: Python interface to EnergyPLAN - Advanced energy system analysis computer model
Author-email: Ché Cameron <research@checameron.com>
Project-URL: Homepage, https://github.com/Atinoda/epnlink
Keywords: energyplan,parse,energy
Classifier: License :: OSI Approved :: GNU General Public License v3 (GPLv3)
Classifier: Programming Language :: Python :: 3
Classifier: Intended Audience :: Science/Research
Classifier: Intended Audience :: Developers
Classifier: Topic :: Scientific/Engineering :: Interface Engine/Protocol Translator
Requires-Python: >=3.9
License-File: LICENSE
Requires-Dist: pandas
Requires-Dist: numpy
